CHANGES.rst
LICENSE
MANIFEST.in
README.rst
setup.cfg
setup.py
cxx2rs/__init__.py
cxx2rs/__main__.py
cxx2rs/parser.py
cxx2rs/rustify.py
cxx2rs/stringify.py
cxx2rs.egg-info/PKG-INFO
cxx2rs.egg-info/SOURCES.txt
cxx2rs.egg-info/dependency_links.txt
cxx2rs.egg-info/entry_points.txt
cxx2rs.egg-info/not-zip-safe
cxx2rs.egg-info/pbr.json
cxx2rs.egg-info/requires.txt
cxx2rs.egg-info/top_level.txt