Metadata-Version: 1.1
Name: cxx2rs
Version: 0.3.8
Summary: A rust-binding generator for C/C++ files
Home-page: https://github.com/manuels/cxx2rs
Author: manuels
Author-email: UNKNOWN
License: UNKNOWN
Platform: UNKNOWN
Classifier: Programming Language :: Python
Classifier: Programming Language :: Python :: 2.7
Classifier: Intended Audience :: Developers
